{
  "players": [
    {
      "id": "aaron-rodgers",
      "name": "Aaron Rodgers",
      "position": "QB",
      "teams": ["GB", "NYJ"],
      "years": [2005, null],
      "numbers": [12, 8],
      "height": "6-2",
      "weight": 225,
      "handedness": "right",
      "colors": ["#ccd5ae", "#FFB612"],
      "stats": {
        "regular-season.general.games": {
          "value": 240,
          "rank": [1, 1]
        },
        "regular-season.passing.completions": {
          "value": 5198,
          "rank": [1, 1]
        },
        "regular-season.passing.attempts": {
          "value": 7977,
          "rank": [1, 1]
        },
        "regular-season.passing.completion-percentage": {
          "value": 65.2,
          "rank": [1, 1]
        },
        "regular-season.passing.yards": {
          "value": 61162,
          "rank": [1, 1]
        },
        "regular-season.passing.touchdowns": {
          "value": 490,
          "rank": [1, 1]
        },
        "regular-season.passing.interceptions": {
          "value": 112,
          "rank": [1, 1]
        },
        "regular-season.passing.rating": {
          "value": 103.0,
          "rank": [1, 1]
        },
        "regular-season.passing.sacks": {
          "value": 551,
          "rank": [1, 1]
        },
        "regular-season.passing.fumbles": {
          "value": 94,
          "rank": [1, 1]
        },
        "regular-season.rushing.attempts": {
          "value": 731,
          "rank": [1, 1]
        },
        "regular-season.rushing.yards": {
          "value": 3509,
          "rank": [1, 1]
        },
        "regular-season.rushing.touchdowns": {
          "value": 35,
          "rank": [1, 1]
        },
        "post-season.general.games": {
          "value": 21,
          "rank": [1, 1]
        },
        "post-season.passing.completions": {
          "value": 501,
          "rank": [1, 1]
        },
        "post-season.passing.attempts": {
          "value": 775,
          "rank": [1, 1]
        },
        "post-season.passing.completion-percentage": {
          "value": 64.7,
          "rank": [1, 1]
        },
        "post-season.passing.yards": {
          "value": 5894,
          "rank": [1, 1]
        },
        "post-season.passing.touchdowns": {
          "value": 45,
          "rank": [1, 1]
        },
        "post-season.passing.interceptions": {
          "value": 13,
          "rank": [1, 1]
        },
        "post-season.passing.rating": {
          "value": 100.1,
          "rank": [1, 1]
        },
        "post-season.passing.sacks": {
          "value": 55,
          "rank": [1, 1]
        },
        "post-season.passing.fumbles": {
          "value": 13,
          "rank": [1, 1]
        },
        "post-season.rushing.attempts": {
          "value": 56,
          "rank": [1, 1]
        },
        "post-season.rushing.yards": {
          "value": 285,
          "rank": [1, 1]
        },
        "post-season.rushing.touchdowns": {
          "value": 4,
          "rank": [1, 1]
        },
        "awards.individual.mvp": {
          "value": 4,
          "rank": [1, 1]
        },
        "awards.individual.sb-mvp": {
          "value": 1,
          "rank": [1, 1]
        },
        "awards.individual.pro-bowl": {
          "value": 10,
          "rank": [1, 1]
        },
        "awards.individual.all-pro-first": {
          "value": 4,
          "rank": [1, 1]
        },
        "awards.individual.all-pro-second": {
          "value": 1,
          "rank": [1, 1]
        },
        "awards.team.sb-appearance": {
          "value": 1,
          "rank": [1, 1]
        },
        "awards.team.sb-win": {
          "value": 1,
          "rank": [1, 1]
        }
      }
    },
    {
      "id": "tom-brady",
      "name": "Tom Brady",
      "position": "QB",
      "teams": ["NE", "TB"],
      "years": [2000, 2022],
      "numbers": [12, 7],
      "height": "6-4",
      "weight": 225,
      "handedness": "right",
      "colors": ["#778da9", "#C60C30", "#B0B7BC"],
      "stats": {
        "regular-season.general.games": {
          "value": 335,
          "rank": [1, 1]
        },
        "regular-season.passing.completions": {
          "value": 7753,
          "rank": [1, 1]
        },
        "regular-season.passing.attempts": {
          "value": 12050,
          "rank": [1, 1]
        },
        "regular-season.passing.completion-percentage": {
          "value": 64.3,
          "rank": [1, 1]
        },
        "regular-season.passing.yards": {
          "value": 89214,
          "rank": [1, 1]
        },
        "regular-season.passing.touchdowns": {
          "value": 649,
          "rank": [1, 1]
        },
        "regular-season.passing.interceptions": {
          "value": 212,
          "rank": [1, 1]
        },
        "regular-season.passing.rating": {
          "value": 97.2,
          "rank": [1, 1]
        },
        "regular-season.passing.sacks": {
          "value": 565,
          "rank": [1, 1]
        },
        "regular-season.passing.fumbles": {
          "value": 134,
          "rank": [1, 1]
        },
        "regular-season.rushing.attempts": {
          "value": 693,
          "rank": [1, 1]
        },
        "regular-season.rushing.yards": {
          "value": 1123,
          "rank": [1, 1]
        },
        "regular-season.rushing.touchdowns": {
          "value": 28,
          "rank": [1, 1]
        },
        "post-season.general.games": {
          "value": 48,
          "rank": [1, 1]
        },
        "post-season.passing.completions": {
          "value": 1200,
          "rank": [1, 1]
        },
        "post-season.passing.attempts": {
          "value": 1921,
          "rank": [1, 1]
        },
        "post-season.passing.completion-percentage": {
          "value": 62.5,
          "rank": [1, 1]
        },
        "post-season.passing.yards": {
          "value": 13400,
          "rank": [1, 1]
        },
        "post-season.passing.touchdowns": {
          "value": 88,
          "rank": [1, 1]
        },
        "post-season.passing.interceptions": {
          "value": 40,
          "rank": [1, 1]
        },
        "post-season.passing.rating": {
          "value": 89.8,
          "rank": [1, 1]
        },
        "post-season.passing.sacks": {
          "value": 81,
          "rank": [1, 1]
        },
        "post-season.passing.fumbles": {
          "value": 16,
          "rank": [1, 1]
        },
        "post-season.rushing.attempts": {
          "value": 114,
          "rank": [1, 1]
        },
        "post-season.rushing.yards": {
          "value": 133,
          "rank": [1, 1]
        },
        "post-season.rushing.touchdowns": {
          "value": 7,
          "rank": [1, 1]
        },
        "awards.individual.mvp": {
          "value": 3,
          "rank": [1, 1]
        },
        "awards.individual.sb-mvp": {
          "value": 5,
          "rank": [1, 1]
        },
        "awards.individual.pro-bowl": {
          "value": 15,
          "rank": [1, 1]
        },
        "awards.individual.all-pro-first": {
          "value": 3,
          "rank": [1, 1]
        },
        "awards.individual.all-pro-second": {
          "value": 3,
          "rank": [1, 1]
        },
        "awards.team.sb-appearance": {
          "value": 10,
          "rank": [1, 1]
        },
        "awards.team.sb-win": {
          "value": 7,
          "rank": [1, 1]
        }
      }
    }
  ]
}
